nbopen/__init__.py
nbopen/__main__.py
nbopen/install_win.py
nbopen/install_xdg.py
nbopen/nbopen.py
winbopen-0.7.2.dist-info/LICENSE
winbopen-0.7.2.dist-info/METADATA
winbopen-0.7.2.dist-info/WHEEL
winbopen-0.7.2.dist-info/top_level.txt
winbopen-0.7.2.dist-info/RECORD
