Metadata-Version: 2.1
Name: winbopen
Version: 0.7.2
Summary: Opens ipynb files on click. Reuses existing jupyter instance if possible.
Home-page: https://github.com/axil/winbopen
Author: Lev Maximov
Author-email: lev.maximov@gmail.com
License: MIT License
Keywords: jupyter,notebook,ipynb
Platform: UNKNOWN
Classifier: Programming Language :: Python :: 3
Classifier: License :: OSI Approved :: MIT License
Classifier: Operating System :: OS Independent
Requires-Dist: notebook
Requires-Dist: psutil
